{"sty":{"w":808,"h":500,"bgc":"#ffffff"},"sym":[{"id":"U-7098","l":"U-7098","cnt":"⬬","sty":{"zi":1,"c":"#595959","ff":"v","fw":"400","o":1,"t":{"trn":[404,191],"s":57.15,"sx":1.11}}},{"id":"U-28390","l":"U-28390","cnt":"𝕱","sty":{"zi":2,"c":"#ff0000","ff":"v","fw":"400","o":1,"t":{"trn":[253,221],"s":20}}},{"id":"U-42585","l":"U-42585","cnt":"𝕲","sty":{"zi":3,"c":"#0a2970","ff":"v","fw":"400","o":1,"t":{"trn":[541,250],"s":25}}},{"id":"U-49683","l":"Clone0ƒ U-7098","cnt":"⬬","sty":{"zi":1,"c":"#ffffff","ff":"v","fw":"400","o":0.43,"t":{"trn":[404,194],"s":51.38,"sx":1.11,"sy":0.95}}}]}